pysubparser/__init__.py
pysubparser/classes/__init__.py
pysubparser/classes/exceptions.py
pysubparser/classes/subtitle.py
pysubparser/cleaners/__init__.py
pysubparser/cleaners/ascii.py
pysubparser/cleaners/brackets.py
pysubparser/cleaners/formatting.py
pysubparser/cleaners/lower_case.py
pysubparser/cleaners/wrap_text.py
pysubparser/parser.py
pysubparser/parsers/__init__.py
pysubparser/parsers/srt.py
pysubparser/parsers/ssa.py
pysubparser/parsers/sub.py
pysubparser/parsers/txt.py
pysubparser/util.py
pysubparser/writer.py
pysubparser/writers/__init__.py
pysubparser/writers/srt.py
pysub_parser-1.7.1.dist-info/LICENSE
pysub_parser-1.7.1.dist-info/WHEEL
pysub_parser-1.7.1.dist-info/METADATA
pysub_parser-1.7.1.dist-info/RECORD
