Metadata-Version: 2.1
Name: pysub-parser
Version: 1.7.1
Summary: Utility to extract the contents of a subtitle file.
Home-page: https://github.com/fedecalendino/pysub-parser
License: MIT
Keywords: parsing,subtitle,srt,ssa,sub
Author: Fede Calendino
Author-email: fede@calendino.com
Requires-Python: >=3.8,<4.0
Classifier: Intended Audience :: Developers
Classifier: License :: OSI Approved :: MIT License
Classifier: Programming Language :: Python :: 3
Classifier: Programming Language :: Python :: 3.8
Classifier: Programming Language :: Python :: 3.9
Classifier: Programming Language :: Python :: 3.10
Classifier: Programming Language :: Python :: 3.11
Classifier: Programming Language :: Python :: 3.10
Classifier: Programming Language :: Python :: 3.8
Classifier: Programming Language :: Python :: 3.9
Requires-Dist: unidecode (>=1.3.4,<2.0.0)
Project-URL: Documentation, https://github.com/fedecalendino/pysub-parser/blob/main/README.md
